fsm_pull/__init__.py
fsm_pull/connection.py
fsm_pull/fsm.py
fsm_pull/protobuf/__init__.py
fsm_pull/protobuf/convert.py
fsm_pull/protobuf/records_pb2.py
fsm_pull-0.2.29.dist-info/entry_points.txt
fsm_pull-0.2.29.dist-info/WHEEL
fsm_pull-0.2.29.dist-info/METADATA
fsm_pull-0.2.29.dist-info/RECORD
