Metadata-Version: 2.1
Name: fsm-pull
Version: 0.2.29
Summary: Tool for downloading data from FSM
Author: Lohith Anandan
Author-email: lohith@vernacular.ai
Requires-Python: >=3.8,<4.0
Classifier: Programming Language :: Python :: 3
Classifier: Programming Language :: Python :: 3.8
Classifier: Programming Language :: Python :: 3.9
Requires-Dist: docopt (>=0.6.2,<0.7.0)
Requires-Dist: loguru (>=0.5.3,<0.6.0)
Requires-Dist: mypy-protobuf (>=2.4,<3.0)
Requires-Dist: requests (>=2.25.1,<3.0.0)
Requires-Dist: tqdm (>=4.62.0,<5.0.0)
Requires-Dist: vivaldi (>=0.2.4,<0.3.0)
